LICENSE
MANIFEST.in
README.rst
setup.py
sentry_youtrack/__init__.py
sentry_youtrack/__init__.pyc
sentry_youtrack/forms.py
sentry_youtrack/forms.pyc
sentry_youtrack/plugin.py
sentry_youtrack/plugin.pyc
sentry_youtrack/tests.pyc
sentry_youtrack/utils.py
sentry_youtrack/utils.pyc
sentry_youtrack/youtrack.py
sentry_youtrack/youtrack.pyc
sentry_youtrack.egg-info/.DS_Store
sentry_youtrack.egg-info/PKG-INFO
sentry_youtrack.egg-info/SOURCES.txt
sentry_youtrack.egg-info/dependency_links.txt
sentry_youtrack.egg-info/entry_points.txt
sentry_youtrack.egg-info/not-zip-safe
sentry_youtrack.egg-info/pbr.json
sentry_youtrack.egg-info/requires.txt
sentry_youtrack.egg-info/top_level.txt
sentry_youtrack/__pycache__/__init__.cpython-34.pyc
sentry_youtrack/static/sentry_youtrack/scripts.js
sentry_youtrack/static/sentry_youtrack/styles.css
sentry_youtrack/templates/sentry_youtrack/assign_issue_form.html
sentry_youtrack/templates/sentry_youtrack/create_issue_form.html
sentry_youtrack/templates/sentry_youtrack/project_conf_form.html
tests/__init__.py
tests/test_api.py
tests/test_form.py