Metadata-Version: 1.1
Name: sentry-youtrack
Version: 0.3.5
Summary: A Sentry extension which integrates with YouTrack
Home-page: http://github.com/bogdal/sentry-youtrack
Author: Adam Bogdał
Author-email: adam@bogdal.pl
License: BSD
Platform: UNKNOWN
Classifier: Framework :: Django
Classifier: Intended Audience :: Developers
Classifier: Intended Audience :: System Administrators
Classifier: Operating System :: OS Independent
Classifier: Topic :: Software Development
Classifier: Programming Language :: Python
Classifier: License :: OSI Approved :: BSD License
